buskit
