Metadata-Version: 1.0
Name: buskit
Version: 1.0.0.dev4
Summary: Bus data analytics and simulation toolkit
Home-page: https://github.com/ywnch/BusSimulator
Author: Yuwen Chang
Author-email: ywchang@nyu.edu
License: MIT
Platform: UNKNOWN
